videofingerprint/__init__.py
videofingerprint/__version__.py
videofingerprint/downloader.py
videofingerprint/exceptions.py
videofingerprint/framesextractor.py
videofingerprint/rlgdcf_videofingerprint.py
videofingerprint/utils.py
videofingerprint/videoduration.py
videofingerprint-0.0.3.dist-info/LICENSE
videofingerprint-0.0.3.dist-info/METADATA
videofingerprint-0.0.3.dist-info/WHEEL
videofingerprint-0.0.3.dist-info/top_level.txt
videofingerprint-0.0.3.dist-info/RECORD
