Metadata-Version: 2.1
Name: videofingerprint
Version: 0.0.3
Summary: Relative Luminance gradient and Dominant Color of Frames (RLGDCF) based Digital Video Fingerprinting. 
Home-page: https://akamhy.github.io/videofingerprint/
Download-URL: https://github.com/akamhy/videofingerprint/archive/0.0.3.tar.gz
Author: Akash Mahanty
Author-email: akamhy@yahoo.com
License: MIT
Project-URL: Source, https://github.com/akamhy/videofingerprint
Project-URL: Tracker, https://github.com/akamhy/videofingerprint/issues
Keywords: Digital video fingerprinting,videofingerprint,duplicate video detection,RLGDCF,find duplicate video,compare videos,video,video diff,Relative Luminance gradient,Dominant Color of Frames
Platform: UNKNOWN
Classifier: Development Status :: 5 - Production/Stable
Classifier: Intended Audience :: Developers
Classifier: Intended Audience :: End Users/Desktop
Classifier: Intended Audience :: Information Technology
Classifier: Topic :: Multimedia :: Video
Classifier: Natural Language :: English
Classifier: Topic :: Scientific/Engineering :: Image Recognition
Classifier: License :: OSI Approved :: MIT License
Classifier: Programming Language :: Python
Classifier: Programming Language :: Python :: 3
Classifier: Programming Language :: Python :: 3.6
Classifier: Programming Language :: Python :: 3.7
Classifier: Programming Language :: Python :: 3.8
Classifier: Programming Language :: Python :: 3.9
Classifier: Programming Language :: Python :: 3.10
Classifier: Programming Language :: Python :: Implementation :: CPython
Requires-Python: >=3.6
License-File: LICENSE
Requires-Dist: imagedominantcolor
Requires-Dist: yt-dlp
